utils_nm/__init__.py
utils_nm/data_functions.py
utils_nm/db_functions.py
utils_nm/orm_models.py
utils_nm/util_classes.py
utils_nm/util_context_managers.py
utils_nm/util_decorators.py
utils_nm/util_functions.py
utils_nm/util_gui_classes.py
utils_nm-1.0.16.dist-info/LICENSE
utils_nm-1.0.16.dist-info/METADATA
utils_nm-1.0.16.dist-info/WHEEL
utils_nm-1.0.16.dist-info/top_level.txt
utils_nm-1.0.16.dist-info/RECORD
