Metadata-Version: 2.1
Name: utils-nm
Version: 1.0.16
Summary: Package for personal utility operations
Author-email: Nikola Maksimovic <nikola.maksimovic@outlook.com>
License: Copyright 2022 Nikola Maksimovic
Project-URL: Homepage, https://github.com/NikoMak/utils_nm
Classifier: Programming Language :: Python :: 3
Classifier: License :: OSI Approved :: MIT License
Classifier: Operating System :: OS Independent
Requires-Python: >=3.10
License-File: LICENSE
Requires-Dist: SQLAlchemy ==2.*
Requires-Dist: pandas ==2.*
Requires-Dist: tqdm ==4.*
Requires-Dist: psutil ==5.*
Requires-Dist: customtkinter ==5.*
